fdb_data/__init__.py
fdb_data/__main__.py
fdb_data/errors.py
fdb_data/parser.py
fdb_data-1.0.20.dist-info/METADATA
fdb_data-1.0.20.dist-info/WHEEL
fdb_data-1.0.20.dist-info/top_level.txt
fdb_data-1.0.20.dist-info/RECORD
