Metadata-Version: 2.1
Name: fdb-data
Version: 1.0.20
Summary: FDB database module
Home-page: http://ppbe.ru
Author: FotonPC
Author-email: foton-pc@inbox.ru
License: MIT
Keywords: database foton fotonpc fdb data big
Platform: UNKNOWN
Classifier: License :: OSI Approved :: MIT License
Classifier: Programming Language :: Python :: 3.8
Requires-Dist: bs4
Requires-Dist: lxml
Requires-Dist: robin-pl
Requires-Dist: evalnumstr
